vochunk/__init__.py
vochunk/models/__init__.py
vochunk/models/reverb/ReverbClassifierNetwork_20240116174852.pt
vochunk/models/reverb/__init__.py
vochunk/models/reverb/data.py
vochunk/models/reverb/inference.py
vochunk/models/reverb/mlp.py
vochunk/models/reverb/train.py
vochunk/models/voice/VoiceNonVoiceClassifier_20240115155819.pt
vochunk/models/voice/__init__.py
vochunk/models/voice/data.py
vochunk/models/voice/inference.py
vochunk/models/voice/mlp.py
vochunk/models/voice/train.py
vochunk/utils/__init__.py
vochunk/utils/utils.py
vochunk/utils/vggish.py
voice-of-chunk/__init__.py
voice-of-chunk/models/__init__.py
voice-of-chunk/models/reverb/__init__.py
voice-of-chunk/models/reverb/data.py
voice-of-chunk/models/reverb/inference.py
voice-of-chunk/models/reverb/mlp.py
voice-of-chunk/models/reverb/train.py
voice-of-chunk/models/voice/__init__.py
voice-of-chunk/models/voice/data.py
voice-of-chunk/models/voice/inference.py
voice-of-chunk/models/voice/mlp.py
voice-of-chunk/models/voice/train.py
voice-of-chunk/utils/__init__.py
voice-of-chunk/utils/utils.py
voice-of-chunk/utils/vggish.py
voice_of_chunk/__init__.py
voice_of_chunk/models/__init__.py
voice_of_chunk/models/reverb/ReverbClassifierNetwork_20240116174852.pt
voice_of_chunk/models/reverb/__init__.py
voice_of_chunk/models/reverb/data.py
voice_of_chunk/models/reverb/inference.py
voice_of_chunk/models/reverb/mlp.py
voice_of_chunk/models/reverb/train.py
voice_of_chunk/models/voice/VoiceNonVoiceClassifier_20240115155819.pt
voice_of_chunk/models/voice/__init__.py
voice_of_chunk/models/voice/data.py
voice_of_chunk/models/voice/inference.py
voice_of_chunk/models/voice/mlp.py
voice_of_chunk/models/voice/train.py
voice_of_chunk/utils/__init__.py
voice_of_chunk/utils/utils.py
voice_of_chunk/utils/vggish.py
vochunk-1.0.0.dist-info/LICENSE
vochunk-1.0.0.dist-info/METADATA
vochunk-1.0.0.dist-info/WHEEL
vochunk-1.0.0.dist-info/top_level.txt
vochunk-1.0.0.dist-info/RECORD
